promised/__init__.py
promised/boiler_property.py
promised/test.py
promised/test_boiler_property.py
promised-1.2.2.dist-info/LICENSE
promised-1.2.2.dist-info/METADATA
promised-1.2.2.dist-info/WHEEL
promised-1.2.2.dist-info/top_level.txt
promised-1.2.2.dist-info/RECORD
