Metadata-Version: 2.1
Name: promised
Version: 1.2.2
Summary: A flexible cached property with get/set/del/init/dependant/cached-mapping capabilities.
Home-page: https://github.com/Andrew-Hogan/Promised
Author: Andrew M. Hogan
Author-email: drewthedruid@gmail.com
License: Apache License 2.0
Platform: any
Classifier: Intended Audience :: Developers
Classifier: Programming Language :: Python :: 3
Classifier: Programming Language :: Python
Classifier: License :: OSI Approved :: Apache Software License
Classifier: Operating System :: OS Independent
Classifier: Topic :: Software Development :: Libraries :: Python Modules
Classifier: Topic :: Utilities
